degenbot/__init__.py
degenbot/anvil_fork.py
degenbot/builder_endpoint.py
degenbot/cache.py
degenbot/chainlink.py
degenbot/config.py
degenbot/constants.py
degenbot/erc20_token.py
degenbot/exceptions.py
degenbot/functions.py
degenbot/logging.py
degenbot/py.typed
degenbot/types.py
degenbot/aerodrome/__init__.py
degenbot/aerodrome/abi.py
degenbot/aerodrome/functions.py
degenbot/aerodrome/managers.py
degenbot/aerodrome/pools.py
degenbot/aerodrome/types.py
degenbot/arbitrage/__init__.py
degenbot/arbitrage/types.py
degenbot/arbitrage/uniswap_2pool_cycle_testing.py
degenbot/arbitrage/uniswap_curve_cycle.py
degenbot/arbitrage/uniswap_lp_cycle.py
degenbot/arbitrage/uniswap_multipool_cycle_testing.py
degenbot/balancer/__init__.py
degenbot/balancer/managers.py
degenbot/balancer/pools.py
degenbot/balancer/types.py
degenbot/balancer/libraries/__init__.py
degenbot/balancer/libraries/constants.py
degenbot/balancer/libraries/fixed_point.py
degenbot/balancer/libraries/helpers.py
degenbot/balancer/libraries/input_helpers.py
degenbot/balancer/libraries/log_exp_math.py
degenbot/balancer/libraries/scaling_helpers.py
degenbot/balancer/libraries/weighted_math.py
degenbot/camelot/__init__.py
degenbot/camelot/abi.py
degenbot/camelot/functions.py
degenbot/camelot/pools.py
degenbot/curve/__init__.py
degenbot/curve/abi.py
degenbot/curve/curve_stableswap_liquidity_pool.py
degenbot/curve/deployments.py
degenbot/curve/types.py
degenbot/managers/__init__.py
degenbot/managers/erc20_token_manager.py
degenbot/pancakeswap/__init__.py
degenbot/pancakeswap/abi.py
degenbot/pancakeswap/managers.py
degenbot/pancakeswap/pools.py
degenbot/registry/__init__.py
degenbot/registry/all_pools.py
degenbot/registry/all_tokens.py
degenbot/solidly/__init__.py
degenbot/solidly/solidly_functions.py
degenbot/sushiswap/abi.py
degenbot/sushiswap/managers.py
degenbot/sushiswap/pools.py
degenbot/transaction/__init__.py
degenbot/transaction/simulation_ledger.py
degenbot/transaction/uniswap_transaction.py
degenbot-0.4.3.dist-info/licenses/LICENSE
degenbot-0.4.3.dist-info/METADATA
degenbot-0.4.3.dist-info/WHEEL
degenbot-0.4.3.dist-info/top_level.txt
degenbot-0.4.3.dist-info/RECORD
