Metadata-Version: 2.4
Name: degenbot
Version: 0.4.3
Summary: Python classes to aid rapid development of Uniswap (V2, V3, V4), Curve V1, and Solidly V2 arbitrage bots on EVM-compatible blockchains
Author-email: BowTiedDevil <devil@bowtieddevil.com>
License: MIT
Project-URL: Homepage, https://www.degencode.com
Project-URL: Repository, https://github.com/BowTiedDevil/degenbot
Project-URL: Tracker, https://github.com/BowTiedDevil/degenbot/issues
Project-URL: Twitter, https://twitter.com/BowTiedDevil
Classifier: Programming Language :: Python :: 3
Classifier: License :: OSI Approved :: MIT License
Classifier: Development Status :: 3 - Alpha
Classifier: Intended Audience :: Developers
Classifier: Natural Language :: English
Classifier: Operating System :: POSIX
Requires-Python: >=3.12
License-File: LICENSE
Requires-Dist: cvxpy<2,>=1.6
Requires-Dist: pydantic<3,>=2.10
Requires-Dist: scipy<1.16,>=1.15
Requires-Dist: watchdog<7,>=6.0
Requires-Dist: web3<8,>=7.9
Dynamic: license-file
